expression_fields/__init__.py
expression_fields/expr.py
expression_fields/fields.py
django_expression_fields-0.4.0.dist-info/LICENSE
django_expression_fields-0.4.0.dist-info/METADATA
django_expression_fields-0.4.0.dist-info/WHEEL
django_expression_fields-0.4.0.dist-info/top_level.txt
django_expression_fields-0.4.0.dist-info/RECORD
