Metadata-Version: 2.1
Name: django-expression-fields
Version: 0.4.0
Summary: django-expression-fields allows typing mathematical expressions into form fields and having only the calculated result stored in the database.
Home-page: http://github.com/vtbassmatt/django-expression-fields/
Author: Matt Cooper
Author-email: vtbassmatt@gmail.com
License: MIT License
Keywords: django field expression math
Platform: UNKNOWN
Classifier: Development Status :: 4 - Beta
Classifier: Environment :: Plugins
Classifier: Environment :: Web Environment
Classifier: Framework :: Django
Classifier: Intended Audience :: Developers
Classifier: License :: OSI Approved :: MIT License
Classifier: Programming Language :: Python
Classifier: Programming Language :: Python :: 2.7
Classifier: Programming Language :: Python :: 3
Classifier: Programming Language :: Python :: 3.4
Classifier: Topic :: Software Development :: Libraries :: Python Modules
License-File: LICENSE
Requires-Dist: django
